besttrack/__init__.py
besttrack/btengine.py
besttrack/plotBestTrack.py
besttrack/readCells.py
besttrack/mapdata/counties/c_11au16.dbf
besttrack/mapdata/counties/c_11au16.prj
besttrack/mapdata/counties/c_11au16.shp
besttrack/mapdata/counties/c_11au16.shx
besttrack/mapdata/provinces/province.dbf
besttrack/mapdata/provinces/province.prj
besttrack/mapdata/provinces/province.shp
besttrack/mapdata/provinces/province.shx
besttrack/mapdata/states/s_11au16.dbf
besttrack/mapdata/states/s_11au16.prj
besttrack/mapdata/states/s_11au16.shp
besttrack/mapdata/states/s_11au16.shx
besttrack-0.2.1.data/scripts/besttrack
besttrack-0.2.1.data/scripts/besttrack.config
besttrack-0.2.1.dist-info/DESCRIPTION.rst
besttrack-0.2.1.dist-info/METADATA
besttrack-0.2.1.dist-info/RECORD
besttrack-0.2.1.dist-info/WHEEL
besttrack-0.2.1.dist-info/metadata.json
besttrack-0.2.1.dist-info/top_level.txt
