Metadata-Version: 2.0
Name: besttrack
Version: 0.2.1
Summary: Object-based geotemporal path optimization
Home-page: https://github.com/arkweather/BestTrack
Author: David Harrison
Author-email: david.r.harrison-1@ou.edu
License: MIT
Keywords: verification,tracking,weather,meteorology
Platform: UNKNOWN
Classifier: Development Status :: 4 - Beta
Classifier: Intended Audience :: Science/Research
Classifier: License :: OSI Approved :: MIT License
Classifier: Programming Language :: Python :: 2
Classifier: Programming Language :: Python :: 2.6
Classifier: Programming Language :: Python :: 2.7
Requires-Dist: basemap (~=1.0.7)
Requires-Dist: beautifulsoup4 (~=4.4.1)
Requires-Dist: matplotlib (~=1.5.1)
Requires-Dist: numpy (~=1.11.1)
Requires-Dist: scipy (~=0.18.0)
Requires-Dist: shapely (~=1.5.16)
